pyfghapitest/__init__.py
pyfghapitest/multiplication.py
pyfghapitest-0.1.0.dist-info/METADATA
pyfghapitest-0.1.0.dist-info/WHEEL
pyfghapitest-0.1.0.dist-info/top_level.txt
pyfghapitest-0.1.0.dist-info/RECORD
